design.sv
// Code your design here
// Code your testbench here
// or browse Examples
//-------------------------------------------------------
//Synchronous FIFO with depth of 32 and width of 16 bits
//Defines can be changed to vary depth and width
//-------------------------------------------------------
`define FIFO_WIDTH 16  //width of each location
`define FIFO_SIZE_BITS 5  //5 bits for counter => 32 deep FIFO
`define FIFO_SIZE ( 1<<`FIFO_SIZE_BITS)

//FIFO ports
module sync_fifo(
  input logic  reset,
  input logic clk,
  input logic write,
  input logic read,   
  input logic [`FIFO_WIDTH-1:0] data_in,                  
  output logic [`FIFO_WIDTH-1:0] data_out,                  
  output logic fifo_empty,
  output logic fifo_full,      
  output logic [`FIFO_SIZE_BITS-1:0] fifo_counter
);             

  //rd and wr pointer for internally writing/read from memory
  logic[`FIFO_SIZE_BITS-1] wr_ptr;
  logic[`FIFO_SIZE_BITS-1] rd_ptr;
  
  //fifo array
  logic [`FIFO_WIDTH-1:0] fifo_mem [`FIFO_SIZE-1:0];
  
  
always @(fifo_counter)
begin
  fifo_empty = (fifo_counter==0);
  fifo_full = (fifo_counter== `FIFO_SIZE);
end

always @(posedge clk or posedge reset)
begin
  if( reset )
     fifo_counter <= 0;
  //write and read happening same clk
  else if( (!fifo_full && write) && ( !fifo_empty && read) )
     fifo_counter <= fifo_counter;
  //write only
  else if( !fifo_full && write)
     fifo_counter <= fifo_counter + 1;
  //read only
  else if( !fifo_empty && read )
     fifo_counter <= fifo_counter - 1;
  else
     fifo_counter <= fifo_counter;
end

always @( posedge clk or posedge reset)
begin
  if( reset )
    data_out <= 0;
  else
  begin
    if( read && !fifo_empty )
      data_out <= fifo_mem[rd_ptr];
    else
      data_out <= data_out;
   end
end

always @(posedge clk)
begin
  if( write && !fifo_full )
    fifo_mem[wr_ptr] <= data_in;
  else
    fifo_mem[wr_ptr] <= fifo_mem[wr_ptr];
end

always@(posedge clk or posedge reset)
begin
  if( reset )
   begin
      wr_ptr <= 0;
      rd_ptr <= 0;
   end
   else
   begin
     if( !fifo_full && write )    
       wr_ptr <= wr_ptr + 1;
     else  wr_ptr <= wr_ptr;

     if( !fifo_empty && read )
       rd_ptr <= rd_ptr + 1;
     else
       rd_ptr <= rd_ptr;
   end
end
  
endmodule

testbench.sv
module testbench;
   logic  reset;
   logic clk;
   logic write;
   logic read;   
   logic [`FIFO_WIDTH-1:0] data_in;                  
   logic [`FIFO_WIDTH-1:0] data_out;                  
   logic fifo_empty;
   logic fifo_full;     
   logic [`FIFO_SIZE_BITS-1:0] fifo_counter;
  sync_fifo inst(reset,clk,write,read,data_in,data_out,fifo_empty,fifo_full,fifo_counter);
   always #10 clk=~clk;
  initial begin
    $dumpfile("dump.vcd");
    $dumpvars(1);
  end
    
  initial begin
    $monitor("Time=%0t counter=%0d full=%0d write_enable=%0d data_in=%0d empty=%0d read_enable=%0d data_out=%0d ",$time,fifo_counter,fifo_full,write,data_in,fifo_empty,read,data_out);
    {clk,write,read,reset}=0;
    #10 reset=1;
    #20 reset=0;
    repeat(16)begin
    #20 write=1; data_in=$urandom_range(0,32);
    end
    #20 read=1;write=0;
    repeat(16)begin
    #20 read=1;
    end
    #20 read=0;
    #200
    $finish;
  end
endmodule

dump.vcd
$date
	Tue Aug 27 07:41:32 2024
$end

$version
	Synopsys VCS version U-2023.03-SP2_Full64
$end

$timescale
	1ns
$end

$comment Csum: 1 ff68abc73087c536 $end


$scope module testbench $end
$var reg 1 ! reset $end
$var reg 1 " clk $end
$var reg 1 # write $end
$var reg 1 $ read $end
$var reg 16 % data_in [15:0] $end
$var reg 16 & data_out [15:0] $end
$var reg 1 ' fifo_empty $end
$var reg 1 ( fifo_full $end
$var reg 5 ) fifo_counter [4:0] $end
$upscope $end

$enddefinitions $end

#0
$dumpvars
0"
x'
x(
0$
0!
0#
bxxxxxxxxxxxxxxxx %
bxxxxxxxxxxxxxxxx &
bxxxxx )
$end
#10
1"
1!
b0000000000000000 &
b00000 )
1'
0(
#20
0"
#30
0!
1"
#40
0"
#50
1#
b0000000000010111 %
1"
b00001 )
0'
#60
0"
#70
b0000000000001011 %
1"
b00010 )
#80
0"
#90
b0000000000010100 %
1"
b00011 )
#100
0"
#110
b0000000000001100 %
1"
b00100 )
#120
0"
#130
b0000000000011101 %
1"
b00101 )
#140
0"
#150
b0000000000001011 %
1"
b00110 )
#160
0"
#170
b0000000000001101 %
1"
b00111 )
#180
0"
#190
b0000000000001010 %
1"
b01000 )
#200
0"
#210
b0000000000010110 %
1"
b01001 )
#220
0"
#230
b0000000000011001 %
1"
b01010 )
#240
0"
#250
1"
b01011 )
#260
0"
#270
b0000000000010100 %
1"
b01100 )
#280
0"
#290
b0000000000011110 %
1"
b01101 )
#300
0"
#310
b0000000000010110 %
1"
b01110 )
#320
0"
#330
b0000000000000110 %
1"
b01111 )
#340
0"
#350
b0000000000001011 %
1"
b10000 )
#360
0"
#370
1$
0#
1"
b0000000000010111 &
b01111 )
#380
0"
#390
1"
b0000000000001011 &
b01110 )
#400
0"
#410
1"
b0000000000010100 &
b01101 )
#420
0"
#430
1"
b0000000000001100 &
b01100 )
#440
0"
#450
1"
b0000000000011101 &
b01011 )
#460
0"
#470
1"
b0000000000001011 &
b01010 )
#480
0"
#490
1"
b0000000000001101 &
b01001 )
#500
0"
#510
1"
b0000000000001010 &
b01000 )
#520
0"
#530
1"
b0000000000010110 &
b00111 )
#540
0"
#550
1"
b0000000000011001 &
b00110 )
#560
0"
#570
1"
b00101 )
#580
0"
#590
1"
b0000000000010100 &
b00100 )
#600
0"
#610
1"
b0000000000011110 &
b00011 )
#620
0"
#630
1"
b0000000000010110 &
b00010 )
#640
0"
#650
1"
b0000000000000110 &
b00001 )
#660
0"
#670
1"
b0000000000001011 &
b00000 )
1'
#680
0"
#690
1"
#700
0"
#710
0$
1"
